myfirstlibtest/__init__.py
myfirstlibtest/example.py
myfirstlibtest-0.0.1.dist-info/LICENSE
myfirstlibtest-0.0.1.dist-info/METADATA
myfirstlibtest-0.0.1.dist-info/WHEEL
myfirstlibtest-0.0.1.dist-info/top_level.txt
myfirstlibtest-0.0.1.dist-info/RECORD
